osbot_utils/__init__.py
osbot_utils/base_classes/Cache_Pickle.py
osbot_utils/base_classes/Kwargs_To_Disk.py
osbot_utils/base_classes/Kwargs_To_Self.py
osbot_utils/base_classes/__init__.py
osbot_utils/context_managers/__init__.py
osbot_utils/context_managers/async_invoke.py
osbot_utils/context_managers/disable_root_loggers.py
osbot_utils/decorators/__init__.py
osbot_utils/decorators/classes/__init__.py
osbot_utils/decorators/classes/singleton.py
osbot_utils/decorators/lists/__init__.py
osbot_utils/decorators/lists/filter_list.py
osbot_utils/decorators/lists/group_by.py
osbot_utils/decorators/lists/index_by.py
osbot_utils/decorators/methods/__init__.py
osbot_utils/decorators/methods/cache.py
osbot_utils/decorators/methods/cache_on_function.py
osbot_utils/decorators/methods/cache_on_self.py
osbot_utils/decorators/methods/cache_on_tmp.py
osbot_utils/decorators/methods/capture_exception.py
osbot_utils/decorators/methods/capture_status.py
osbot_utils/decorators/methods/catch.py
osbot_utils/decorators/methods/context.py
osbot_utils/decorators/methods/depreciated.py
osbot_utils/decorators/methods/function_type_check.py
osbot_utils/decorators/methods/obj_as_context.py
osbot_utils/decorators/methods/remove_return_value.py
osbot_utils/decorators/methods/required_fields.py
osbot_utils/fluent/Fluent_Dict.py
osbot_utils/fluent/Fluent_List.py
osbot_utils/fluent/__init__.py
osbot_utils/helpers/CFormat.py
osbot_utils/helpers/CPrint.py
osbot_utils/helpers/Dependency_Manager.py
osbot_utils/helpers/Dict_To_Attr.py
osbot_utils/helpers/Hashicorp_Secrets.py
osbot_utils/helpers/Local_Cache.py
osbot_utils/helpers/Local_Caches.py
osbot_utils/helpers/Print_Table.py
osbot_utils/helpers/Python_Audit.py
osbot_utils/helpers/Random_Seed.py
osbot_utils/helpers/Str_ASCII.py
osbot_utils/helpers/Type_Registry.py
osbot_utils/helpers/Zip_Bytes.py
osbot_utils/helpers/__init__.py
osbot_utils/helpers/ast/Ast.py
osbot_utils/helpers/ast/Ast_Base.py
osbot_utils/helpers/ast/Ast_Data.py
osbot_utils-3.72.0.dist-info/LICENSE
osbot_utils-3.72.0.dist-info/METADATA
osbot_utils-3.72.0.dist-info/WHEEL
osbot_utils-3.72.0.dist-info/RECORD
